kubesplit/__init__.py
kubesplit/__main__.py
kubesplit/args.py
kubesplit/config.py
kubesplit/convert.py
kubesplit/errors.py
kubesplit/helpers.py
kubesplit/k8s_descriptor.py
kubesplit/kubesplit.py
kubesplit/namespaces.py
kubesplit/output.py
kubesplit-0.4.0.dist-info/METADATA
kubesplit-0.4.0.dist-info/WHEEL
kubesplit-0.4.0.dist-info/entry_points.txt
kubesplit-0.4.0.dist-info/licenses/LICENSE
kubesplit-0.4.0.dist-info/RECORD
