Metadata-Version: 2.4
Name: kubesplit
Version: 0.4.0
Summary: A CLI to split multidoc yaml formatted kubernetes descriptors to a set of single resource files
Project-URL: Repository, https://github.com/looztra/kubesplit
Author-email: Christophe Furmaniak <christophe.furmaniak@gmail.com>
License-Expression: Apache-2.0
License-File: LICENSE
Classifier: Programming Language :: Python :: 3
Classifier: Programming Language :: Python :: 3.10
Classifier: Programming Language :: Python :: 3.11
Classifier: Programming Language :: Python :: 3.12
Classifier: Topic :: Utilities
Requires-Python: >=3.10
Requires-Dist: yamkix>=0.10.0
